idegrity_identity/__init__.py
idegrity_identity/async_identity_api.py
idegrity_identity/identity_api.py
idegrity_identity-0.1.5.dist-info/LICENSE
idegrity_identity-0.1.5.dist-info/METADATA
idegrity_identity-0.1.5.dist-info/WHEEL
idegrity_identity-0.1.5.dist-info/top_level.txt
idegrity_identity-0.1.5.dist-info/RECORD
