Metadata-Version: 2.1
Name: idegrity-identity
Version: 0.1.5
Summary: Python Wrapper for Idegrity's Identity services
Author: Cookie
Author-email: cookie@idegrity.com
Requires-Python: >=3.9
License-File: LICENSE
Requires-Dist: httpx
Requires-Dist: aiofiles
Requires-Dist: requests
